gcp_stocks/__init__.py
gcp_stocks/myfunctions.py
gcp_stocks-0.1.0.dist-info/METADATA
gcp_stocks-0.1.0.dist-info/WHEEL
gcp_stocks-0.1.0.dist-info/top_level.txt
gcp_stocks-0.1.0.dist-info/RECORD
