Metadata-Version: 2.1
Name: gcp-stocks
Version: 0.1.0
Summary: My first Python library
Home-page: UNKNOWN
Author: OhOh1
Author-email: UNKNOWN
License: MIT
Platform: UNKNOWN
